README.md
requirements.txt
setup.py
pt_lambda_util.egg-info/PKG-INFO
pt_lambda_util.egg-info/SOURCES.txt
pt_lambda_util.egg-info/dependency_links.txt
pt_lambda_util.egg-info/requires.txt
pt_lambda_util.egg-info/top_level.txt
src/__init__.py
src/ptCommonUtil.py
src/ptDynamoDb.py
src/ptLogger.py
src/ptMetric.py
src/ptMongoDb.py
src/ptTrace.py
src/inner_folder/__init__.py
src/inner_folder/ptDynamoDb_2.py